{
  "metadata": {
    "url": "http://192.168.8.233:3000/strategies",
    "featureId": "FEAT-063",
    "criterionId": "ac-001",
    "version": 24,
    "capturedAt": "2025-12-16T03:12:50.553Z",
    "pageTitle": "Portfolio AI Platform",
    "viewport": {
      "width": 1280,
      "height": 720
    },
    "captureTimeMs": 18539
  },
  "console": {
    "errorCount": 5,
    "warningCount": 0,
    "errors": [
      {
        "text": "Failed to load resource: the server responded with a status of 404 (Not Found)",
        "source": "http://192.168.8.233:3000/api/strategies:0"
      },
      {
        "text": "Failed to load resource: the server responded with a status of 404 (Not Found)",
        "source": "http://192.168.8.233:3000/api/strategies:0"
      },
      {
        "text": "Failed to load resource: the server responded with a status of 404 (Not Found)",
        "source": "http://192.168.8.233:3000/api/strategies:0"
      },
      {
        "text": "Failed to load resource: the server responded with a status of 404 (Not Found)",
        "source": "http://192.168.8.233:3000/api/strategies:0"
      },
      {
        "text": "WebSocket connection to 'ws://192.168.8.233:3000/_next/webpack-hmr?id=jcl6uzwn57vgypmzAMPAq' failed: Error in connection establishment: net::ERR_CONNECTION_REFUSED",
        "source": "http://192.168.8.233:3000/_next/static/chunks/node_modules_next_dist_client_aaee43fe._.js:10116"
      }
    ],
    "warnings": []
  },
  "network": {
    "totalRequests": 29,
    "failedRequests": 1,
    "failures": [
      {
        "url": "http://192.168.8.233:3000/api/strategies",
        "status": 404
      }
    ],
    "slowRequests": []
  },
  "pageState": {
    "hasContent": true,
    "visibleTextSample": "Portfolio AI Dashboard Portfolio Watchlist Trading Backtest Strategies Picks System Market Closed AI Strategies Research-backed trading strategies generated by autonomous agents Generate Strategies",
    "keyElements": {
      "tables": 0,
      "charts": 1,
      "buttons": 7,
      "errorMessages": 0,
      "loadingSpinners": 0,
      "emptyStates": 0
    }
  },
  "performance": {
    "pageLoadMs": 468,
    "domContentLoadedMs": 210,
    "largestContentfulPaintMs": 532
  }
}